{
  "projects": [
    {
      "id": "1786",
      "text": "fsdfs",
      "budget": "34234",
      "category": {
        "id": "3",
        "name": "Desing"
      },
      "cost": 0,
      "services": []
    },
    {
      "id": "06db",
      "text": "dfsdfs",
      "budget": "3424",
      "category": {
        "id": "2",
        "name": "Desenvolvimento"
      },
      "cost": 0,
      "services": []
    },
    {
      "id": "9551",
      "text": "dfsdf",
      "budget": "432423",
      "category": {
        "id": "4",
        "name": "Planejamento"
      },
      "cost": 0,
      "services": []
    },
    {
      "id": "3cb4",
      "text": "fdsfsd",
      "budget": "4324",
      "cost": 0,
      "services": []
    },
    {
      "id": "4663",
      "text": "fsdf",
      "budget": "321",
      "cost": 0,
      "services": []
    },
    {
      "id": "ad3e",
      "text": "fsdfds",
      "budget": "31231",
      "cost": 0,
      "services": []
    },
    {
      "id": "6207",
      "text": "fasdf",
      "budget": "34242",
      "category": {
        "id": "2",
        "name": "Desenvolvimento"
      },
      "cost": 0,
      "services": []
    },
    {
      "id": "4e1f",
      "text": "fsdfasdf",
      "budget": "3123",
      "cost": 0,
      "services": []
    },
    {
      "id": "3b8e",
      "text": "teste de um nome grande",
      "budget": "100",
      "cost": 20,
      "services": [
        {
          "name": "novo servico ",
          "cost": "10",
          "description": "servico para testar a aplicaçao",
          "id": "7b9c486b-62a0-41b4-9307-7cd33390ecdc"
        },
        {
          "name": "servicoboa",
          "cost": "20",
          "id": "feb3c1af-ad11-4a21-9bcb-77af6d8f87d0"
        }
      ]
    }
  ],
  "categories": [
    {
      "id": "1",
      "name": "Infra"
    },
    {
      "id": "2",
      "name": "Desenvolvimento"
    },
    {
      "id": "3",
      "name": "Desing"
    },
    {
      "id": "4",
      "name": "Planejamento"
    }
  ]
}